dry_django/__init__.py
dry_django/contrib/__init__.py
dry_django/contrib/rest_framework/__init__.py
dry_django/contrib/rest_framework/handlers.py
dry_django/contrib/rest_framework/mixins.py
dry_django/contrib/rest_framework/pagination.py
dry_django/contrib/rest_framework/serializers.py
dry_django/contrib/rest_framework/utils.py
dry_django/contrib/rest_framework/views.py
dry_django/exceptions.py
dry_django/selectors/__init__.py
dry_django/selectors/generic.py
dry_django/selectors/mixins.py
dry_django/services/__init__.py
dry_django/services/generic.py
dry_django/services/mixins.py
dry_django/utils/__init__.py
dry_django/utils/validators.py
dry_django-0.3.12.dist-info/WHEEL
dry_django-0.3.12.dist-info/METADATA
dry_django-0.3.12.dist-info/RECORD
